gc_meox_tms/__init__.py
gc_meox_tms/__main__.py
gc_meox_tms/derivatization.py
gc_meox_tms/utils.py
gc_meox_tms-1.0.1.dist-info/LICENSE
gc_meox_tms-1.0.1.dist-info/METADATA
gc_meox_tms-1.0.1.dist-info/WHEEL
gc_meox_tms-1.0.1.dist-info/top_level.txt
gc_meox_tms-1.0.1.dist-info/RECORD
