Metadata-Version: 2.1
Name: gc-meox-tms
Version: 1.0.1
Summary: In-silico MeOX/TMS derivatization of chemical compounds
Author-email: Ales Krenek <ljocha@ics.muni.cz>, Maksym Skoryk <maksym.skoryk@recetox.muni.cz>
Maintainer-email: RECETOX <GalaxyToolsDevelopmentandDeployment@space.muni.cz>
Project-URL: Homepage, https://github.com/RECETOX/gc-meox-tms
Classifier: Programming Language :: Python :: 3
Classifier: License :: OSI Approved :: MIT License
Classifier: Operating System :: OS Independent
Requires-Python: >=3.8
License-File: LICENSE
Requires-Dist: rdkit-pypi
Provides-Extra: dev
Requires-Dist: flake8 ; extra == 'dev'
Requires-Dist: mock ; extra == 'dev'
Requires-Dist: pytest ; extra == 'dev'
Requires-Dist: pytest-cov ; extra == 'dev'
Requires-Dist: pytest-rerunfailures ; extra == 'dev'
Provides-Extra: eda
Requires-Dist: jupyter ; extra == 'eda'
Requires-Dist: py3Dmol ; extra == 'eda'
